{"cand_id":"1874","nombre":"HERNAN DARIO ECHEVERRI ARBOLEDA","org":"PARTIDO LIBERAL COLOMBIANO","corp":"CAMARA DE REPRESENTANTES","corp_id":1,"circ_id":"3","org_id":"6","total_ingresos":20000000.0,"total_gastos":20000000.0,"num_ingresos":2,"num_gastos":2,"ingresos":[{"id_ingreso":11086,"nom_ingreso":"Donación de especie honorarios como gerente de campaña","des_ingreso":"Donación de especie honorarios como gerente de campaña","nom_formato":"102 - 6.2B CONTRIBUCIONES, DONACIONES Y CRÉDITOS, EN DINERO O ESPECIE, QUE REALICEN LOS PARTICULARES","codigo":"102","total":"10000000","nombre_persona":"DALJER ASCANIO CAMACHO","nit_cedula":"1037635059","tipo_contribucion":5,"especie":"10000000","donacion":"0","credito":"0","aporte":"0","fecha_registro_movimiento":"2025-12-08","no_comprobante_interno":"002","acta_no":"001","archivo":"archivos/archivos_ingresos/2026-03-17soporteIngreso_RkocGPiCNM.pdf"},{"id_ingreso":11084,"nom_ingreso":"Donación en especie honorarios de contador durante a campaña","des_ingreso":"Donación en especie honorarios de contador durante a campaña","nom_formato":"102 - 6.2B CONTRIBUCIONES, DONACIONES Y CRÉDITOS, EN DINERO O ESPECIE, QUE REALICEN LOS PARTICULARES","codigo":"102","total":"10000000","nombre_persona":"SARA MELISSA TAVERA CASTAÑO","nit_cedula":"1216715815","tipo_contribucion":5,"especie":"10000000","donacion":"0","credito":"0","aporte":"0","fecha_registro_movimiento":"2025-12-08","no_comprobante_interno":"001","acta_no":"001","archivo":"archivos/archivos_ingresos/2026-04-15soporteIngreso_zDVLMpp8On.pdf"}],"gastos":[{"id_gasto":38625,"nom_formato":"207 -  GASTOS JUDICIALES Y DE RENDICIÓN DE CUENTAS","codigo":"207","total":"10000000","nombre_persona":"DALJER ASCANIO CAMACHO","nit_cedula":"1037635059","fecha_registro_movimiento":"2025-12-08","no_comprobante_interno":"002","archivo":"archivos/archivos_gastos/2026-03-17soporteGasto_pS9d6EQ2uP.pdf"},{"id_gasto":38622,"nom_formato":"207 -  GASTOS JUDICIALES Y DE RENDICIÓN DE CUENTAS","codigo":"207","total":"10000000","nombre_persona":"SARA MELISSA TAVERA CASTAO","nit_cedula":"1216715815","fecha_registro_movimiento":"2025-12-08","no_comprobante_interno":"001","archivo":"archivos/archivos_gastos/2026-04-15soporteGasto_NputgZZYDM.pdf"}],"contador":{"nombre":"SARA MELISSA TAVERA CASTAO","documento":"1216715815","tarjeta":"241417-T","email":"sarameli94@hotmail.com","telefono":"3005250105"},"gerente":{"nombre":"DALJER ASCANIO CAMACHO","documento":"1037635059","banco":"BANCO DAVIVIENDA","cuenta":"488470990810","tipo_cta":"Cuenta de Ahorros","email":"daljera94@gmail.com","telefono":"3126989026"},"ani":{},"cedula":"1037635059"}