{"cand_id":"2075","nombre":"CARLOS ALBERTO ARISTIZABAL MONTES","org":"MOVIMIENTO SALVACIÓN NACIONAL","corp":"CAMARA DE REPRESENTANTES","corp_id":1,"circ_id":"3","org_id":"3","total_ingresos":2000000.0,"total_gastos":2000000.0,"num_ingresos":2,"num_gastos":2,"ingresos":[{"id_ingreso":1808,"nom_ingreso":"Donación en especie servicios contables","des_ingreso":"Donación en especie del servicio representado en prestación de servicios contables ,a la campaña del Candidato Carlos \r\nAlberto Aristizábal Montes aspirante a Cámara del Departamento de Caldas","nom_formato":"102 - 6.2B CONTRIBUCIONES, DONACIONES Y CRÉDITOS, EN DINERO O ESPECIE, QUE REALICEN LOS PARTICULARES","codigo":"102","total":"1000000","nombre_persona":"GERALDINE LONDOÑO BERMUDEZ","nit_cedula":"1010021835","tipo_contribucion":5,"especie":"1000000","donacion":"0","credito":"0","aporte":"0","fecha_registro_movimiento":"2026-02-09","no_comprobante_interno":"02","acta_no":"02","archivo":"archivos/archivos_ingresos/2026-02-15soporteIngreso_iuEN9hkLRW.pdf"},{"id_ingreso":1807,"nom_ingreso":"Donación especie servicios como gerente de campaña","des_ingreso":"Donación en especie del  servicio representado en servicios como gerente de campaña, los cuales fueron brindados de manera voluntaria, a la campaña del  Candidato Carlos Alberto Aristizábal Montes aspirante a Cámara. del Departamento de  Caldas","nom_formato":"102 - 6.2B CONTRIBUCIONES, DONACIONES Y CRÉDITOS, EN DINERO O ESPECIE, QUE REALICEN LOS PARTICULARES","codigo":"102","total":"1000000","nombre_persona":"JOSÉ OMAR OCAMPO PÉREZ","nit_cedula":"15990522","tipo_contribucion":5,"especie":"1000000","donacion":"0","credito":"0","aporte":"0","fecha_registro_movimiento":"2026-01-30","no_comprobante_interno":"01","acta_no":"01","archivo":"archivos/archivos_ingresos/2026-02-15soporteIngreso_xfookU5kku.pdf"}],"gastos":[{"id_gasto":5464,"nom_formato":"207 -  GASTOS JUDICIALES Y DE RENDICIÓN DE CUENTAS","codigo":"207","total":"1000000","nombre_persona":"JOSÉ OMAR OCAMPO PÉREZ","nit_cedula":"15990522","fecha_registro_movimiento":"2026-02-06","no_comprobante_interno":"02","archivo":"archivos/archivos_gastos/2026-02-25soporteGasto_hrx5QINXwi.pdf"},{"id_gasto":5462,"nom_formato":"207 -  GASTOS JUDICIALES Y DE RENDICIÓN DE CUENTAS","codigo":"207","total":"1000000","nombre_persona":"GERALDINE LONDOÑO BERMUDEZ","nit_cedula":"1010021835","fecha_registro_movimiento":"2026-02-05","no_comprobante_interno":"01","archivo":"archivos/archivos_gastos/2026-02-25soporteGasto_1f82CCoFrU.pdf"}],"contador":{"nombre":"GERALDINE LONDONO BERMUDEZ","documento":"1010021835","tarjeta":"287974-T","email":"geralbermudez03@gmail.com","telefono":"3234913871"},"gerente":{"nombre":"JOSE OMAR OCAMPO PEREZ","documento":"15990522","banco":"BANCOLOMBIA","cuenta":"37300003898","tipo_cta":"Cuenta Corriente","email":"jomarocampoperez@gmail.com","telefono":"3117084276"},"ani":{},"cedula":"15990522"}