{"cand_id":"1441","nombre":"ANDRES GERARDO VILLOTA GOMEZ","org":"MOVIMIENTO SALVACIÓN NACIONAL","corp":"CAMARA DE REPRESENTANTES","corp_id":1,"circ_id":"3","org_id":"3","total_ingresos":18500000.0,"total_gastos":18500000.0,"num_ingresos":4,"num_gastos":4,"ingresos":[{"nom_ingreso":"crédito cuenta por pagar Honorarios gerente de campaña","des_ingreso":"crédito cuenta por pagar Honorarios gerente de campaña","nom_formato":"102 - 6.2B CONTRIBUCIONES, DONACIONES Y CRÉDITOS, EN DINERO O ESPECIE, QUE REALICEN LOS PARTICULARES","codigo":"102","total":"2000000","nombre_persona":"ANA VERONICA CRUZ LEON","nit_cedula":"51672668","tipo_contribucion":3,"especie":"0","donacion":"0","credito":"2000000","aporte":"0","fecha_registro_movimiento":"2026-03-26","no_comprobante_interno":"04","acta_no":"04"},{"nom_ingreso":"Crédito cuentas por pagar honorarios asesoría de marketing","des_ingreso":"Crédito cuentas por pagar honorarios asesoría de marketing","nom_formato":"102 - 6.2B CONTRIBUCIONES, DONACIONES Y CRÉDITOS, EN DINERO O ESPECIE, QUE REALICEN LOS PARTICULARES","codigo":"102","total":"2000000","nombre_persona":"JAIRO BETANCOURT FERNANDÉZ","nit_cedula":"80421373","tipo_contribucion":3,"especie":"0","donacion":"0","credito":"2000000","aporte":"0","fecha_registro_movimiento":"2026-03-26","no_comprobante_interno":"03","acta_no":"03"},{"nom_ingreso":"crédito cuentas por pagar Honorarios asesoria juridica y legal","des_ingreso":"crédito cuentas por pagar Honorarios asesoria juridica y legal","nom_formato":"102 - 6.2B CONTRIBUCIONES, DONACIONES Y CRÉDITOS, EN DINERO O ESPECIE, QUE REALICEN LOS PARTICULARES","codigo":"102","total":"11000000","nombre_persona":"JOSÉ LEOPOLDO VARGAS RODRIGUÉZ","nit_cedula":"3263802","tipo_contribucion":3,"especie":"0","donacion":"0","credito":"11000000","aporte":"0","fecha_registro_movimiento":"2026-03-27","no_comprobante_interno":"02","acta_no":"02"},{"nom_ingreso":"crédito cuenta por pagar honorarios contador de campaña","des_ingreso":"crédito cuenta por pagar honorarios contador de campaña","nom_formato":"102 - 6.2B CONTRIBUCIONES, DONACIONES Y CRÉDITOS, EN DINERO O ESPECIE, QUE REALICEN LOS PARTICULARES","codigo":"102","total":"3500000","nombre_persona":"GABRIEL VILLAMIZAR LIZCANO","nit_cedula":"1013607416","tipo_contribucion":3,"especie":"0","donacion":"0","credito":"3500000","aporte":"0","fecha_registro_movimiento":"2026-03-21","no_comprobante_interno":"01","acta_no":"01"}],"gastos":[{"nom_formato":"207 -  GASTOS JUDICIALES Y DE RENDICIÓN DE CUENTAS","codigo":"207","total":"2000000","nombre_persona":"ANA VERONICA CRUZ LEON","nit_cedula":"51672668","fecha_registro_movimiento":"2026-03-26","no_comprobante_interno":"04"},{"nom_formato":"201 - 6.8B GASTOS DE ADMINISTRACIÓN","codigo":"201","total":"2000000","nombre_persona":"JAIRO BETANCOURT FERNANDÉZ","nit_cedula":"80421373","fecha_registro_movimiento":"2026-03-26","no_comprobante_interno":"03"},{"nom_formato":"207 -  GASTOS JUDICIALES Y DE RENDICIÓN DE CUENTAS","codigo":"207","total":"11000000","nombre_persona":"JOSÉ LEOPOLDO VARGAS RODRIGUÉZ","nit_cedula":"3263802","fecha_registro_movimiento":"2026-03-27","no_comprobante_interno":"02"},{"nom_formato":"207 -  GASTOS JUDICIALES Y DE RENDICIÓN DE CUENTAS","codigo":"207","total":"3500000","nombre_persona":"GABRIEL VILLAMIZAR LIZCANO","nit_cedula":"1013607416","fecha_registro_movimiento":"2026-03-21","no_comprobante_interno":"01"}],"contador":{"nombre":"GABRIEL VILLAMIZAR LIZCANO","documento":"1013607416","tarjeta":"262038-T","email":"gabrielvillamizar1989@gmail.com","telefono":"3124502020"},"gerente":{"nombre":"ANA VERONICA CRUZ LEON","documento":"51672668","banco":"BANCOLOMBIA","cuenta":"662-000037-32","tipo_cta":"Cuenta Corriente","email":"veronica.cruz6274@gmail.com","telefono":"3167503867"},"ani":{},"cedula":"51672668"}