{"cand_id":"1717","nombre":"EMILSE MARIA GONZALEZ JIMENEZ","org":"MOVIMIENTO SALVACIÓN NACIONAL","corp":"CAMARA DE REPRESENTANTES","corp_id":1,"circ_id":"3","org_id":"3","total_ingresos":6450000.0,"total_gastos":6450000.0,"num_ingresos":3,"num_gastos":3,"ingresos":[{"nom_ingreso":"Donación voluntaria para financiación de campaña.","des_ingreso":"Donación de impresión de 500 volantes para campaña.","nom_formato":"102 - 6.2B CONTRIBUCIONES, DONACIONES Y CRÉDITOS, EN DINERO O ESPECIE, QUE REALICEN LOS PARTICULARES","codigo":"102","total":"450000","nombre_persona":"EMILSE MARIA GONZALEZ JIMENEZ","nit_cedula":"1065573439","tipo_contribucion":5,"especie":"450000","donacion":"0","credito":"0","aporte":"0","fecha_registro_movimiento":"2026-01-08","no_comprobante_interno":"101","acta_no":"12"},{"nom_ingreso":"DONACION EN ESPECIE - SERVICIOS CONTABLES","des_ingreso":"Donacion en en especie correspondiente a la prestacion de servicios profesionales de contabilidad para la campaña electoral, realizada por el contador Jersson La Torre Manzano.","nom_formato":"102 - 6.2B CONTRIBUCIONES, DONACIONES Y CRÉDITOS, EN DINERO O ESPECIE, QUE REALICEN LOS PARTICULARES","codigo":"102","total":"3000000","nombre_persona":"JERSSON LA TORRE MANZANO","nit_cedula":"1091656912","tipo_contribucion":5,"especie":"3000000","donacion":"0","credito":"0","aporte":"0","fecha_registro_movimiento":"2026-03-08","no_comprobante_interno":"01","acta_no":"001"},{"nom_ingreso":"Aporte en especie - gerencia de campaña","des_ingreso":"donacion en especie correspondiente a los servicios de gerencia de campaña prestados durante el proceso electoral","nom_formato":"102 - 6.2B CONTRIBUCIONES, DONACIONES Y CRÉDITOS, EN DINERO O ESPECIE, QUE REALICEN LOS PARTICULARES","codigo":"102","total":"3000000","nombre_persona":"CARLOS SNHEYDER TORRES ARRIETA","nit_cedula":"1012400661","tipo_contribucion":5,"especie":"3000000","donacion":"0","credito":"0","aporte":"0","fecha_registro_movimiento":"2026-03-08","no_comprobante_interno":"002","acta_no":"002"}],"gastos":[{"nom_formato":"203 - 6.9B INVERSION EN MATERIALES Y PUBLICACIONES","codigo":"203","total":"450000","nombre_persona":"EMILSE MARIA GONZALEZ JIMENEZ","nit_cedula":"1065573439","fecha_registro_movimiento":"2026-01-08","no_comprobante_interno":"03"},{"nom_formato":"207 -  GASTOS JUDICIALES Y DE RENDICIÓN DE CUENTAS","codigo":"207","total":"3000000","nombre_persona":"JERSSON LATORRE MANZANO","nit_cedula":"1091656912","fecha_registro_movimiento":"2026-03-07","no_comprobante_interno":"02"},{"nom_formato":"207 -  GASTOS JUDICIALES Y DE RENDICIÓN DE CUENTAS","codigo":"207","total":"3000000","nombre_persona":"CARLOS SNHEYDER TORRES ARRIETA","nit_cedula":"1012400661","fecha_registro_movimiento":"2026-03-08","no_comprobante_interno":"01"}],"contador":{"nombre":"JERSSON LA TORRE MANZANO","documento":"1091656912","tarjeta":"152822-T","email":"jerssonlatorremanzano@hotmail.com","telefono":"3136221195"},"gerente":{"nombre":"CARLOS SNHEYDER TORRES ARRIETA","documento":"1012400661","banco":"BANCOLOMBIA","cuenta":"91297805245","tipo_cta":"Cuenta de Ahorros","email":"snheydertorres07@gmail.com","telefono":"3134672401"},"ani":{},"cedula":"1012400661"}