{"cand_id":"1825","nombre":"DIANA CAROLINA LOPEZ SANCHEZ","org":"PARTIDO LIBERAL COLOMBIANO","corp":"CAMARA DE REPRESENTANTES","corp_id":1,"circ_id":"3","org_id":"6","total_ingresos":30000000.0,"total_gastos":30000000.0,"num_ingresos":2,"num_gastos":2,"ingresos":[{"nom_ingreso":"DONACIÓN EN ESPECIE HONORARIOS CONTADOR","des_ingreso":"DONACIÓN EN ESPECIE HONORARIOS CONTADOR","nom_formato":"102 - 6.2B CONTRIBUCIONES, DONACIONES Y CRÉDITOS, EN DINERO O ESPECIE, QUE REALICEN LOS PARTICULARES","codigo":"102","total":"15000000","nombre_persona":"JUAN PABLO ROMERO SANCHEZ","nit_cedula":"1022442974","tipo_contribucion":5,"especie":"15000000","donacion":"0","credito":"0","aporte":"0","fecha_registro_movimiento":"2025-12-08","no_comprobante_interno":"02","acta_no":"01"},{"nom_ingreso":"DONACIÓN EN ESPECIE HONORARIOS GERENTE","des_ingreso":"DONACIÓN EN ESPECIE HONORARIOS GERENTE","nom_formato":"102 - 6.2B CONTRIBUCIONES, DONACIONES Y CRÉDITOS, EN DINERO O ESPECIE, QUE REALICEN LOS PARTICULARES","codigo":"102","total":"15000000","nombre_persona":"JUANITA LAFAURIE LOPEZ","nit_cedula":"1013263205","tipo_contribucion":5,"especie":"15000000","donacion":"0","credito":"0","aporte":"0","fecha_registro_movimiento":"2025-12-08","no_comprobante_interno":"01","acta_no":"01"}],"gastos":[{"nom_formato":"207 -  GASTOS JUDICIALES Y DE RENDICIÓN DE CUENTAS","codigo":"207","total":"15000000","nombre_persona":"JUAN PABLO ROMERO SANCHEZ","nit_cedula":"1022442974","fecha_registro_movimiento":"2026-03-08","no_comprobante_interno":"02"},{"nom_formato":"207 -  GASTOS JUDICIALES Y DE RENDICIÓN DE CUENTAS","codigo":"207","total":"15000000","nombre_persona":"JUANITA LAFAURIE LOPEZ","nit_cedula":"1013263205","fecha_registro_movimiento":"2026-03-08","no_comprobante_interno":"01"}],"contador":{"nombre":"JUAN PABLO ROMERO SANCHEZ","documento":"1022442974","tarjeta":"326572-T","email":"juan@gmail.com","telefono":"6 0 1 2 6 6 4 1 1 1"},"gerente":{"nombre":"JUANITA LAFARURIE LOPEZ","documento":"1013263205","banco":"BANCO CAJA SOCIAL","cuenta":"24153546444","tipo_cta":"Cuenta de Ahorros","email":"JUANITA@GMAIL.COM","telefono":"300 3724847"},"ani":{},"cedula":"1013263205"}