{"cand_id":"562","nombre":"ALIX DEL CARMEN RICARDO PEREZ","org":"PARTIDO CONSERVADOR COLOMBIANO","corp":"SENADO DE LA REPUBLICA","corp_id":4,"circ_id":"13","org_id":"4","total_ingresos":6000000.0,"total_gastos":5974700.0,"num_ingresos":1,"num_gastos":13,"ingresos":[{"nom_ingreso":"prestamo","des_ingreso":"prestamo campaña politica senado de la republica 2026","nom_formato":"102 - 6.2B CONTRIBUCIONES, DONACIONES Y CRÉDITOS, EN DINERO O ESPECIE, QUE REALICEN LOS PARTICULARES","codigo":"102","total":"6000000","nombre_persona":"PARTIDO CONSERVADOR COLOMBIANO","nit_cedula":"860.040.845-1","tipo_contribucion":3,"especie":"0","donacion":"0","credito":"6000000","aporte":"0","fecha_registro_movimiento":"2026-02-17","no_comprobante_interno":"001","acta_no":"001"}],"gastos":[{"nom_formato":"204 - 6.10B ACTOS PÚBLICOS","codigo":"204","total":"262700","nombre_persona":"RAPELUCHES","nit_cedula":"901378140-5","fecha_registro_movimiento":"2026-02-26","no_comprobante_interno":"sje4859","lugar_evento":"barranquilla"},{"nom_formato":"203 - 6.9B INVERSION EN MATERIALES Y PUBLICACIONES","codigo":"203","total":"340000","nombre_persona":"SUMINISTROS XEROX  S.A.S","nit_cedula":"900703598-1","fecha_registro_movimiento":"2026-02-28","no_comprobante_interno":"256"},{"nom_formato":"203 - 6.9B INVERSION EN MATERIALES Y PUBLICACIONES","codigo":"203","total":"252000","nombre_persona":"COMERCIAL PAPELERA S.A.","nit_cedula":"860528396-9","fecha_registro_movimiento":"2026-02-26","no_comprobante_interno":"226422"},{"nom_formato":"203 - 6.9B INVERSION EN MATERIALES Y PUBLICACIONES","codigo":"203","total":"75000","nombre_persona":"LA AGENCIA GRAFICA","nit_cedula":"900836497-3","fecha_registro_movimiento":"2026-02-21","no_comprobante_interno":"1074"},{"nom_formato":"203 - 6.9B INVERSION EN MATERIALES Y PUBLICACIONES","codigo":"203","total":"108000","nombre_persona":"PUNTOS DORADOS CAMISETAS S.A.","nit_cedula":"901880544-8","fecha_registro_movimiento":"2026-02-21","no_comprobante_interno":"066325"},{"nom_formato":"207 -  GASTOS JUDICIALES Y DE RENDICIÓN DE CUENTAS","codigo":"207","total":"700000","nombre_persona":"JOSE DEMOCLITO NEIRA HERRERA","nit_cedula":"91222262","fecha_registro_movimiento":"2026-03-08","no_comprobante_interno":"008"},{"nom_formato":"207 -  GASTOS JUDICIALES Y DE RENDICIÓN DE CUENTAS","codigo":"207","total":"600000","nombre_persona":"EDUARDO ALFREDO POSDA","nit_cedula":"8679700","fecha_registro_movimiento":"2026-03-08","no_comprobante_interno":"007"},{"nom_formato":"203 - 6.9B INVERSION EN MATERIALES Y PUBLICACIONES","codigo":"203","total":"305000","nombre_persona":"LEIDY MARCELA ARANGO","nit_cedula":"1117501813","fecha_registro_movimiento":"2026-02-22","no_comprobante_interno":"001"},{"nom_formato":"204 - 6.10B ACTOS PÚBLICOS","codigo":"204","total":"650000","nombre_persona":"RAFAEL ANTONIO CASTRO VERGARA","nit_cedula":"78107234","fecha_registro_movimiento":"2026-02-24","no_comprobante_interno":"001","lugar_evento":"Bogota"},{"nom_formato":"208 - 6.12B PROPAGANDA ELECTORAL","codigo":"208","total":"1552000","nombre_persona":"CESAR AUGUSTO MARTINEZ RICARDO","nit_cedula":"80221608","fecha_registro_movimiento":"2026-02-24","no_comprobante_interno":"001"},{"nom_formato":"205 - 6.11B SERVICIO DE TRANSPORTE Y CORREO","codigo":"205","total":"350000","nombre_persona":"CECIL DE JESUS CUAO RODRIGUEZ","nit_cedula":"79535422","fecha_registro_movimiento":"2026-02-22","no_comprobante_interno":"0002"},{"nom_formato":"205 - 6.11B SERVICIO DE TRANSPORTE Y CORREO","codigo":"205","total":"600000","nombre_persona":"OSCAR MAURICIO NEIRA RICARDO","nit_cedula":"1032426319","fecha_registro_movimiento":"2026-02-24","no_comprobante_interno":"0001"},{"nom_formato":"203 - 6.9B INVERSION EN MATERIALES Y PUBLICACIONES","codigo":"203","total":"180000","nombre_persona":"GRUPO EFI MOLA","nit_cedula":"901249308-1","fecha_registro_movimiento":"2026-02-21","no_comprobante_interno":"0000"}],"contador":{"nombre":"EDUARDO ALFREDO POSADA PENATE","documento":"8679700","tarjeta":"22564.T","email":"eduardoalfredo04@hotmail.com","telefono":"3106198459"},"gerente":{"nombre":"JOSE DEMOCLITO NEIRA HERRERA","documento":"91222262","banco":"BANCOLOMBIA","cuenta":"18600008092","tipo_cta":"Cuenta Corriente","email":"neirajose92@gmail.com","telefono":"3197670761"},"ani":{},"cedula":"91222262"}