{"cand_id":"623","nombre":"ANDRES  ROJAS MARULANDA","org":"PARTIDO DE LA UNIÓN POR LA GENTE - PARTIDO DE LA U","corp":"SENADO DE LA REPUBLICA","corp_id":4,"circ_id":"13","org_id":"5","total_ingresos":19902800.0,"total_gastos":19885278.42,"num_ingresos":6,"num_gastos":7,"ingresos":[{"nom_ingreso":"APOYO INTITUCIONAL PARA LA CAMPAÑA","des_ingreso":"APOYO INTITUCIONAL PARA LA CAMPAÑA","nom_formato":"102 - 6.2B CONTRIBUCIONES, DONACIONES Y CRÉDITOS, EN DINERO O ESPECIE, QUE REALICEN LOS PARTICULARES","codigo":"102","total":"3000000","nombre_persona":"PARTIDO DE LA UNION POR LA GENTE - PARTIDO DE LA U","nit_cedula":"830124379-1","tipo_contribucion":4,"especie":"0","donacion":"3000000","credito":"0","aporte":"0","fecha_registro_movimiento":"2026-03-03","no_comprobante_interno":"006","acta_no":"DAFPU- 358-21"},{"nom_ingreso":"APOYO INTITUCIONAL PARA LA CAMPAÑA","des_ingreso":"APOYO INTITUCIONAL PARA LA CAMPAÑA","nom_formato":"102 - 6.2B CONTRIBUCIONES, DONACIONES Y CRÉDITOS, EN DINERO O ESPECIE, QUE REALICEN LOS PARTICULARES","codigo":"102","total":"3000000","nombre_persona":"PARTIDO DE LA UNION POR LA GENTE - PARTIDO DE LA U","nit_cedula":"830124379-1","tipo_contribucion":4,"especie":"0","donacion":"3000000","credito":"0","aporte":"0","fecha_registro_movimiento":"2026-02-25","no_comprobante_interno":"005","acta_no":"DAFPU- 234-21"},{"nom_ingreso":"DONACION EN ESPECIE KIT FE- 3173 PARA LA CAMPAÑA","des_ingreso":"DONACION EN ESPECIE KIT FE- 3173 PARA LA CAMPAÑA","nom_formato":"102 - 6.2B CONTRIBUCIONES, DONACIONES Y CRÉDITOS, EN DINERO O ESPECIE, QUE REALICEN LOS PARTICULARES","codigo":"102","total":"4902800","nombre_persona":"PARTIDO DE LA UNION POR LA GENTE - PARTIDO DE LA U","nit_cedula":"830124379-1","tipo_contribucion":5,"especie":"4902800","donacion":"0","credito":"0","aporte":"0","fecha_registro_movimiento":"2026-02-12","no_comprobante_interno":"004","acta_no":"DAFPU-158-21"},{"nom_ingreso":"RECURSOS PROPIOS PARA LA CAMPAÑA","des_ingreso":"RECURSOS PROPIOS PARA LA CAMPAÑA","nom_formato":"101 - 6.1B CRÉDITOS O APORTES QUE PROVENGAN DEL PATRIMONIO DE LOS CANDIDATOS, DE SUS CÓNYUGES O DE SUS COMPAÑEROS PERMANENTES, O DE SUS PARIENTES","codigo":"101","total":"2000000","nombre_persona":"ANDRES  ROJAS MARULANDA","nit_cedula":"94383742","tipo_contribucion":1,"especie":"0","donacion":"0","credito":"0","aporte":"2000000","fecha_registro_movimiento":"2026-02-10","no_comprobante_interno":"003"},{"nom_ingreso":"APOYO INTITUCIONAL PARA LA CAMPAÑA","des_ingreso":"APOYO INTITUCIONAL PARA LA CAMPAÑA","nom_formato":"102 - 6.2B CONTRIBUCIONES, DONACIONES Y CRÉDITOS, EN DINERO O ESPECIE, QUE REALICEN LOS PARTICULARES","codigo":"102","total":"5000000","nombre_persona":"PARTIDO DE LA UNION POR LA GENTE - PARTIDO DE LA U","nit_cedula":"830124379-1","tipo_contribucion":4,"especie":"0","donacion":"5000000","credito":"0","aporte":"0","fecha_registro_movimiento":"2026-01-26","no_comprobante_interno":"002","acta_no":"DAFPU-123-21"},{"nom_ingreso":"APOYO INTITUCIONAL PARA LA CAMPAÑA","des_ingreso":"APOYO INTITUCIONAL PARA LA CAMPAÑA","nom_formato":"102 - 6.2B CONTRIBUCIONES, DONACIONES Y CRÉDITOS, EN DINERO O ESPECIE, QUE REALICEN LOS PARTICULARES","codigo":"102","total":"2000000","nombre_persona":"PARTIDO DE LA UNION POR LA GENTE - PARTIDO DE LA U","nit_cedula":"830124379-1","tipo_contribucion":4,"especie":"0","donacion":"2000000","credito":"0","aporte":"0","fecha_registro_movimiento":"2025-12-18","no_comprobante_interno":"001","acta_no":"DAFPU-021-21"}],"gastos":[{"nom_formato":"209 -  COSTOS FINANCIEROS","codigo":"209","total":"222478.42","nombre_persona":"BANCO AV VILLAS","nit_cedula":"860035827-5","fecha_registro_movimiento":"2026-03-08","no_comprobante_interno":"007"},{"nom_formato":"201 - 6.8B GASTOS DE ADMINISTRACIÓN","codigo":"201","total":"2760000","nombre_persona":"DANIEL MOSQUERA SUAREZ","nit_cedula":"1111810896","fecha_registro_movimiento":"2026-03-08","no_comprobante_interno":"006"},{"nom_formato":"201 - 6.8B GASTOS DE ADMINISTRACIÓN","codigo":"201","total":"2900000","nombre_persona":"BRANDON GUSTAVO RAMIREZ RAMIREZ","nit_cedula":"1151963264","fecha_registro_movimiento":"2026-03-08","no_comprobante_interno":"005"},{"nom_formato":"201 - 6.8B GASTOS DE ADMINISTRACIÓN","codigo":"201","total":"4100000","nombre_persona":"ANGELICA MARIA DIAZ GIL","nit_cedula":"38555454","fecha_registro_movimiento":"2026-03-08","no_comprobante_interno":"004"},{"nom_formato":"207 -  GASTOS JUDICIALES Y DE RENDICIÓN DE CUENTAS","codigo":"207","total":"1000000","nombre_persona":"MARTHA LILIA DIAZ CHACON","nit_cedula":"52694620","fecha_registro_movimiento":"2026-03-05","no_comprobante_interno":"003"},{"nom_formato":"207 -  GASTOS JUDICIALES Y DE RENDICIÓN DE CUENTAS","codigo":"207","total":"4000000","nombre_persona":"DIANA PAOLA PEREZ GUENGUE","nit_cedula":"38551100","fecha_registro_movimiento":"2026-02-15","no_comprobante_interno":"002"},{"nom_formato":"208 - 6.12B PROPAGANDA ELECTORAL","codigo":"208","total":"4902800","nombre_persona":"DICOES GRUPO PUBLICITARIO SAS","nit_cedula":"901336804-6","fecha_registro_movimiento":"2026-02-12","no_comprobante_interno":"001"}],"contador":{"nombre":"MARTHA LILIA DIAZ CHACON","documento":"52694620","tarjeta":"341098 – T","email":"2026eleccionescongreso@gmail.com","telefono":"3042397255"},"gerente":{"nombre":"DIANA PAOLA PEREZ GUENGUE","documento":"38551100","banco":"AV VILLAS","cuenta":"149780053","tipo_cta":"Cuenta de Ahorros","email":"diana.perez.usb@gmail.com","telefono":"3015273951"},"ani":{},"cedula":"38551100"}